vmmc_model/__init__.py
vmmc_model/model.py
Virtual_MMC-0.1.2.dist-info/LICENSE
Virtual_MMC-0.1.2.dist-info/METADATA
Virtual_MMC-0.1.2.dist-info/WHEEL
Virtual_MMC-0.1.2.dist-info/top_level.txt
Virtual_MMC-0.1.2.dist-info/RECORD
