Metadata-Version: 2.1
Name: Virtual-MMC
Version: 0.1.2
Summary: A brief description of your package
Home-page: https://github.com/James-Broster/VMMC
Author: James_Broster
Author-email: james.broster@st-annes.ox.ac.uk
License: MIT
Platform: UNKNOWN
Classifier: Programming Language :: Python :: 3
Classifier: License :: OSI Approved :: MIT License
Classifier: Operating System :: OS Independent
License-File: LICENSE
Requires-Dist: numpy
Requires-Dist: matplotlib
